{"status":"done","publicPath":"http://127.0.0.1:8080/","chunks":{"about":[{"name":"js/about.js","publicPath":"http://127.0.0.1:8080/js/about.js","path":"C:\\Users\\Reeya Tamrakar\\Desktop\\mart\\frontend\\dist\\js\\about.js"},{"name":"about.bf7095b2ffb2bf18b2ea.hot-update.js","publicPath":"http://127.0.0.1:8080/about.bf7095b2ffb2bf18b2ea.hot-update.js","path":"C:\\Users\\Reeya Tamrakar\\Desktop\\mart\\frontend\\dist\\about.bf7095b2ffb2bf18b2ea.hot-update.js"}],"app":[{"name":"js/app.js","publicPath":"http://127.0.0.1:8080/js/app.js","path":"C:\\Users\\Reeya Tamrakar\\Desktop\\mart\\frontend\\dist\\js\\app.js"}]},"error":"ModuleError","message":"Module Error (from ./node_modules/@vue/cli-service/node_modules/vue-loader-v16/dist/index.js):\n\nVueCompilerError: Attribute value was expected.\nat C:\\Users\\Reeya Tamrakar\\Desktop\\mart\\frontend\\src\\views\\Product.vue:12:31\n11 |              <div class='product-img'>\n12 |                <img src='' alt=>\n13 |              </div>\n   |           ^\n14 |            </div>\n15 |          </div>\n"}